probycapi.abi3.so
probycapi/bind.c
probycapi/libmypy.h
probycapi/algo.h
probycapi/algo.c
probycapi/libmypy.c
proby-0.0.13.dist-info/LICENSE
proby-0.0.13.dist-info/WHEEL
proby-0.0.13.dist-info/top_level.txt
proby-0.0.13.dist-info/METADATA
proby-0.0.13.dist-info/RECORD
examples/__init__.py
examples/delta.py
examples/tennis.py
