Metadata-Version: 2.2
Name: proby
Version: 0.0.13
Summary: A package to compute probailities of complex match structures.
Author-email: Marco Milanta <marco.milanta@gmail.com>
Project-URL: Homepage, https://github.com/mmilanta/probable-spork
Project-URL: Issues, https://github.com/mmilanta/probable-spork/issues
Classifier: Programming Language :: Python :: 3
Classifier: License :: OSI Approved :: MIT License
Classifier: Operating System :: OS Independent
Requires-Python: >=3.9
License-File: LICENSE
